mlauto/__init__.py
mlauto/mlauto.py
mynacode/__init__.py
mynacode/mynacode - Copy.py
mynacode/mynacode.py
mynacode-2.0.82.dist-info/METADATA
mynacode-2.0.82.dist-info/WHEEL
mynacode-2.0.82.dist-info/top_level.txt
mynacode-2.0.82.dist-info/RECORD
