Metadata-Version: 2.1
Name: mynacode
Version: 2.0.82
Summary: UNKNOWN
Home-page: https://github.com/ansariminhaj/mynacode_pip
Author: Minhaj Ansari
License: MIT
Platform: UNKNOWN
Classifier: Intended Audience :: Science/Research
Classifier: Programming Language :: Python :: 3
Requires-Dist: numpy
Requires-Dist: dill
Requires-Dist: pyyaml
